oecd_toolbox/__init__.py
oecd_toolbox/converters.py
oecd_toolbox/csv_writers.py
oecd_toolbox/downloaders.py
oecd_toolbox-0.4.3.dist-info/LICENSE
oecd_toolbox-0.4.3.dist-info/METADATA
oecd_toolbox-0.4.3.dist-info/WHEEL
oecd_toolbox-0.4.3.dist-info/top_level.txt
oecd_toolbox-0.4.3.dist-info/RECORD
