Metadata-Version: 2.1
Name: oecd-toolbox
Version: 0.4.3
Summary: OECD fetcher building templates and helpers
Home-page: https://gitlab.algobank.oecd.org/oecd-data-fetchers1/OECD-TOOLBOX
Author: Gyorgy Gyomai, Isaac Afambo, Alena Brin
Author-email: gyorgy.gyomai@oecd.org
Project-URL: Bug Tracker, https://gitlab.algobank.oecd.org/oecd-data-fetchers1/OECD-TOOLBOX/-/issues
Classifier: Programming Language :: Python :: 3
Classifier: License :: OSI Approved :: MIT License
Classifier: Operating System :: OS Independent
Requires-Python: >=3.9
License-File: LICENSE
Requires-Dist: dbnomics-fetcher-toolbox ==0.0.9
Requires-Dist: dbnomics-data-model ==0.13.20
Requires-Dist: python-slugify >=5.0.2
